bpytop.py
themes/adapta.theme
themes/default_black.theme
themes/dracula.theme
themes/dusklight.theme
themes/flat-remix-light.theme
themes/flat-remix.theme
themes/greyscale.theme
themes/gruvbox_dark.theme
themes/kyli0x.theme
themes/matcha-dark-sea.theme
themes/monokai.theme
themes/nord.theme
themes/solarized_dark.theme
themes/whiteout.theme
bpytop-1.0.67.dist-info/entry_points.txt
bpytop-1.0.67.dist-info/LICENSE
bpytop-1.0.67.dist-info/WHEEL
bpytop-1.0.67.dist-info/METADATA
bpytop-1.0.67.dist-info/RECORD
