Metadata-Version: 2.1
Name: bpytop
Version: 1.0.67
Summary: Resource monitor that shows usage and stats for processor, memory, disks, network and processes.
Home-page: https://github.com/aristocratos/bpytop
License: Apache-2.0
Author: Aristocratos
Author-email: jakob@qvantnet.com
Requires-Python: >=3.7,<4.0
Classifier: License :: OSI Approved :: Apache Software License
Classifier: Programming Language :: Python :: 3
Classifier: Programming Language :: Python :: 3.7
Classifier: Programming Language :: Python :: 3.8
Classifier: Programming Language :: Python :: 3.9
Requires-Dist: psutil (>=5.7.0,<6.0.0)
